Metadata-Version: 2.1
Name: odoo-addon-stock_move_forced_lot
Version: 17.0.1.0.0.3
Requires-Python: >=3.10
Requires-Dist: odoo>=17.0a,<17.1dev
Summary: This module allows you to set a lot_id in a procurement to force the stock move generated to only reserve the selected lot.
Home-page: https://github.com/OCA/stock-logistics-workflow
License: LGPL-3
Author: ForgeFlow, Odoo Community Association (OCA)
Author-email: support@odoo-community.org
Classifier: Programming Language :: Python
Classifier: Framework :: Odoo
Classifier: Framework :: Odoo :: 17.0
Classifier: License :: OSI Approved :: GNU Lesser General Public License v3 (LGPLv3)
